pylibi2c.cpython-39-arm-linux-gnueabihf.so
pylibi2c-0.2.1.dist-info/LICENSE
pylibi2c-0.2.1.dist-info/METADATA
pylibi2c-0.2.1.dist-info/WHEEL
pylibi2c-0.2.1.dist-info/top_level.txt
pylibi2c-0.2.1.dist-info/RECORD
