Metadata-Version: 2.1
Name: pylibi2c
Version: 0.2.1
Summary: Linux userspace i2c operation library
Home-page: https://github.com/amaork/libi2c
Author: Amaork
Author-email: amaork <amaork@gmail.com>
License: The MIT License (MIT)
Project-URL: Homepage, https://github.com/amaork/libi2c
Project-URL: Bug Tracker, https://github.com/amaork/libi2c/issues
Keywords: i2c,raspberry-pi
Classifier: License :: OSI Approved :: MIT License
Classifier: Operating System :: POSIX :: Linux
Classifier: Programming Language :: C
Classifier: Programming Language :: Python
Classifier: Programming Language :: Python :: 2
Classifier: Programming Language :: Python :: 3
Requires-Python: >=2.7
License-File: LICENSE
